wudaoai/__init__.py
wudaoai/api_request.py
wudaoai/base_request.py
wudaoai/utils/__init__.py
wudaoai/utils/rsa_util.py
wudaoai-1.2.5.dist-info/METADATA
wudaoai-1.2.5.dist-info/WHEEL
wudaoai-1.2.5.dist-info/top_level.txt
wudaoai-1.2.5.dist-info/RECORD
